Clynton-1.10.3.data/scripts/clynton-run.bat
Clynton-1.10.3.data/scripts/clynton.bat
clynton/Builtins.py
clynton/BytecodeCaching.py
clynton/Bytecodes.py
clynton/CacheCleanup.py
clynton/Constants.py
clynton/Errors.py
clynton/MainControl.py
clynton/ModuleRegistry.py
clynton/OptionParsing.py
clynton/Options.py
clynton/OutputDirectories.py
clynton/PostProcessing.py
clynton/Progress.py
clynton/PythonFlavors.py
clynton/PythonOperators.py
clynton/PythonVersions.py
clynton/Serialization.py
clynton/SourceCodeReferences.py
clynton/Tracing.py
clynton/TreeXML.py
clynton/Variables.py
clynton/Version.py
clynton/__init__.py
clynton/__main__.py
clynton/__past__.py
clynton/build/CCompilerVersion.scons
clynton/build/DataComposerInterface.py
clynton/build/SconsCaching.py
clynton/build/SconsCompilerSettings.py
clynton/build/SconsHacks.py
clynton/build/SconsInterface.py
clynton/build/SconsProgress.py
clynton/build/SconsSpawn.py
clynton/build/SconsUtils.py
clynton/build/Simplfy.scons
clynton/build/__init__.py
clynton/build/randomBack.scons
clynton/build/include/clynton/allocator.h
clynton/build/include/clynton/builtins.h
clynton/build/include/clynton/calling.h
clynton/build/include/clynton/checkers.h
clynton/build/include/clynton/checksum_tools.h
clynton/build/include/clynton/compiled_asyncgen.h
clynton/build/include/clynton/compiled_cell.h
clynton/build/include/clynton/compiled_coroutine.h
clynton/build/include/clynton/compiled_frame.h
clynton/build/include/clynton/compiled_function.h
clynton/build/include/clynton/compiled_generator.h
clynton/build/include/clynton/compiled_method.h
clynton/build/include/clynton/constants.h
clynton/build/include/clynton/constants_blob.h
clynton/build/include/clynton/exception_groups.h
clynton/build/include/clynton/exceptions.h
clynton/build/include/clynton/filesystem_paths.h
clynton/build/include/clynton/freelists.h
clynton/build/include/clynton/hedley.h
clynton/build/include/clynton/helpers.h
clynton/build/include/clynton/importing.h
Clynton-1.10.3.dist-info/LICENSE.txt
Clynton-1.10.3.dist-info/METADATA
Clynton-1.10.3.dist-info/WHEEL
Clynton-1.10.3.dist-info/desktop.ini
Clynton-1.10.3.dist-info/entry_points.txt
Clynton-1.10.3.dist-info/top_level.txt
Clynton-1.10.3.dist-info/RECORD
