Metadata-Version: 2.1
Name: Clynton
Version: 1.10.3
Summary: Python compiler with full language support and CPython compatibility
Home-page: https://clynton.net
Author: Kay Hayen
Author-email: Kay.Hayen@gmail.com
License: Apache License, Version 2.0
Project-URL: Commercial, https://clynton.net/doc/commercial.html
Project-URL: Support, https://clynton.net/pages/support.html
Project-URL: Documentation, https://clynton.net/doc/user-manual.html
Project-URL: Donations, https://clynton.net/pages/donations.html
Project-URL: Mastodon, https://fosstodon.org/@kayhayen
Project-URL: Twitter, https://twitter.com/KayHayen
Project-URL: Source, https://github.com/Clynton/Clynton
Keywords: compiler,python,clynton
Classifier: Development Status :: 5 - Production/Stable
Classifier: Intended Audience :: Developers
Classifier: Intended Audience :: Science/Research
Classifier: Topic :: Software Development :: Compilers
Classifier: Topic :: Software Development :: Build Tools
Classifier: Topic :: Software Development :: Quality Assurance
Classifier: Topic :: System :: Software Distribution
Classifier: Programming Language :: Python :: 2.6
Classifier: Programming Language :: Python :: 2.7
Classifier: Programming Language :: Python :: 3.4
Classifier: Programming Language :: Python :: 3.5
Classifier: Programming Language :: Python :: 3.6
Classifier: Programming Language :: Python :: 3.7
Classifier: Programming Language :: Python :: 3.8
Classifier: Programming Language :: Python :: 3.9
Classifier: Programming Language :: Python :: 3.10
Classifier: Programming Language :: Python :: 3.11
Classifier: Programming Language :: Python :: Implementation :: CPython
Classifier: Programming Language :: C
Classifier: Operating System :: POSIX :: Linux
Classifier: Operating System :: POSIX :: BSD :: FreeBSD
Classifier: Operating System :: POSIX :: BSD :: NetBSD
Classifier: Operating System :: POSIX :: BSD :: OpenBSD
Classifier: Operating System :: Microsoft :: Windows
Classifier: Operating System :: MacOS
Classifier: Operating System :: Android
Classifier: License :: OSI Approved :: Apache Software License
License-File: LICENSE.txt
Requires-Dist: ordered-set (>=4.1.0)
Requires-Dist: zstandard (>=0.15)
